images/ca_logo.png
shell_scripts/checkipcon.sh
shell_scripts/localbandchange.sh
src/__init__.py
src/main.py
src/gui/__init__.py
src/gui/helpers.py
src/gui/neighborhood_list.py
src/gui/scripts.py
src/tests/__init__.py
src/tests/test_helpers.py
src/tests/test_neighborhood_list.py
venv/bin/rst2html.py
venv/bin/rst2html4.py
venv/bin/rst2html5.py
venv/bin/rst2latex.py
venv/bin/rst2man.py
venv/bin/rst2odt.py
venv/bin/rst2odt_prepstyles.py
venv/bin/rst2pseudoxml.py
venv/bin/rst2s5.py
venv/bin/rst2xetex.py
venv/bin/rst2xml.py
venv/bin/rstpep2html.py
s60z-0.2.5.dist-info/LICENSE.rst
s60z-0.2.5.dist-info/METADATA
s60z-0.2.5.dist-info/WHEEL
s60z-0.2.5.dist-info/entry_points.txt
s60z-0.2.5.dist-info/top_level.txt
s60z-0.2.5.dist-info/RECORD
