Metadata-Version: 2.1
Name: s60z
Version: 0.2.5
Summary: Package for s60z GUI, a user interface for signal generation on an SDR
Author-email: "Battieste, Nahjay" <nahjaybattieste@gmail.com>, "Hunter, Christerpher" <djhunter67@gmail.com>
Project-URL: Source, https://github.com/cellantenna/s60z
Classifier: Programming Language :: Python :: 3
Classifier: License :: Other/Proprietary License
Classifier: Operating System :: POSIX :: Linux
Requires-Python: >=3.10
License-File: LICENSE.rst
Requires-Dist: dearpygui
Requires-Dist: serial
Requires-Dist: colorama
Requires-Dist: numpy
Requires-Dist: pytest
Requires-Dist: pathlib
Provides-Extra: test
Requires-Dist: pytest (>=7.3.2) ; extra == 'test'
Requires-Dist: pytest-asyncio (>=0.21.0) ; extra == 'test'
Requires-Dist: pytest-cov (>=4.1.0) ; extra == 'test'
